pycompatlayer.py
PyCompatLayer-0.0.10.dist-info/DESCRIPTION.rst
PyCompatLayer-0.0.10.dist-info/METADATA
PyCompatLayer-0.0.10.dist-info/RECORD
PyCompatLayer-0.0.10.dist-info/WHEEL
PyCompatLayer-0.0.10.dist-info/metadata.json
PyCompatLayer-0.0.10.dist-info/top_level.txt
PyCompatLayer-0.0.10.dist-info/zip-safe
